intersect_sdk-0.8.3.dist-info/METADATA
intersect_sdk-0.8.3.dist-info/WHEEL
intersect_sdk-0.8.3.dist-info/entry_points.txt
intersect_sdk-0.8.3.dist-info/licenses/LICENSE
intersect_sdk/__init__.py
intersect_sdk/_internal/__init__.py
intersect_sdk/_internal/constants.py
intersect_sdk/_internal/control_plane/__init__.py
intersect_sdk/_internal/control_plane/brokers/__init__.py
intersect_sdk/_internal/control_plane/brokers/amqp_client.py
intersect_sdk/_internal/control_plane/brokers/broker_client.py
intersect_sdk/_internal/control_plane/brokers/mqtt_client.py
intersect_sdk/_internal/control_plane/control_plane_manager.py
intersect_sdk/_internal/control_plane/discovery_service.py
intersect_sdk/_internal/control_plane/topic_handler.py
intersect_sdk/_internal/data_plane/__init__.py
intersect_sdk/_internal/data_plane/data_plane_manager.py
intersect_sdk/_internal/data_plane/minio_utils.py
intersect_sdk/_internal/event_metadata.py
intersect_sdk/_internal/exceptions.py
intersect_sdk/_internal/function_metadata.py
intersect_sdk/_internal/interfaces.py
intersect_sdk/_internal/logger.py
intersect_sdk/_internal/messages/__init__.py
intersect_sdk/_internal/messages/event.py
intersect_sdk/_internal/messages/lifecycle.py
intersect_sdk/_internal/messages/userspace.py
intersect_sdk/_internal/multi_flag_thread_event.py
intersect_sdk/_internal/pydantic_schema_generator.py
intersect_sdk/_internal/schema.py
intersect_sdk/_internal/stoppable_thread.py
intersect_sdk/_internal/utils.py
intersect_sdk/_internal/version.py
intersect_sdk/_internal/version_resolver.py
intersect_sdk/app_lifecycle.py
intersect_sdk/capability/__init__.py
intersect_sdk/capability/base.py
intersect_sdk/client.py
intersect_sdk/client_callback_definitions.py
intersect_sdk/config/__init__.py
intersect_sdk/config/client.py
intersect_sdk/config/service.py
intersect_sdk/config/shared.py
intersect_sdk/constants.py
intersect_sdk/core_definitions.py
intersect_sdk/py.typed
intersect_sdk/schema.py
intersect_sdk/service.py
intersect_sdk/service_callback_definitions.py
intersect_sdk/service_definitions.py
intersect_sdk/shared_callback_definitions.py
intersect_sdk/version.py
intersect_sdk-0.8.3.dist-info/RECORD
