Metadata-Version: 2.1
Name: intersect-sdk
Version: 0.8.3
Summary: Python SDK to interact with INTERSECT
Keywords: intersect
Author-Email: Lance Drane <dranelt@ornl.gov>, Marshall McDonnell <mcdonnellmt@ornl.gov>, Seth Hitefield <hitefieldsd@ornl.gov>, Andrew Ayres <ayresaf@ornl.gov>, Gregory Cage <cagege@ornl.gov>, Jesse McGaha <mcgahajr@ornl.gov>, Robert Smith <smithrw@ornl.gov>, Gavin Wiggins <wigginsg@ornl.gov>, Michael Brim <brimmj@ornl.gov>, Rick Archibald <archibaldrk@ornl.gov>, Addi Malviya Thakur <malviyaa@ornl.gov>
License: BSD-3-Clause
Classifier: Programming Language :: Python :: 3
Classifier: Programming Language :: Python :: 3.8
Classifier: Programming Language :: Python :: 3.9
Classifier: Programming Language :: Python :: 3.10
Classifier: Programming Language :: Python :: 3.11
Project-URL: Homepage, https://github.com/INTERSECT-SDK/python-sdk/
Project-URL: Changelog, https://github.com/INTERSECT-SDK/python-sdk/blob/main/CHANGELOG.md
Project-URL: Documentation, https://intersect-python-sdk.readthedocs.io/en/latest/
Project-URL: Issues, https://github.com/INTERSECT-SDK/python-sdk/issues
Requires-Python: <4.0,>=3.8.10
Requires-Dist: pydantic>=2.7.0
Requires-Dist: retrying<2.0.0,>=1.3.4
Requires-Dist: paho-mqtt<2.0.0,>=1.6.1
Requires-Dist: minio>=7.2.3
Requires-Dist: jsonschema[format-nongpl]>=4.21.1
Requires-Dist: eval-type-backport>=0.1.3; python_version < "3.10"
Provides-Extra: amqp
Requires-Dist: pika<2.0.0,>=1.3.2; extra == "amqp"
Provides-Extra: docs
Requires-Dist: sphinx>=5.3.0; extra == "docs"
Requires-Dist: furo>=2023.3.27; extra == "docs"
